MANIFEST.in
README.rst
setup.py
scanningegs/__init__.py
scanningegs/egsinp.py
scanningegs/options.toml
scanningegs/scanningegs.py
scanningegs/template.egsinp
scanningegs.egg-info/PKG-INFO
scanningegs.egg-info/SOURCES.txt
scanningegs.egg-info/dependency_links.txt
scanningegs.egg-info/entry_points.txt
scanningegs.egg-info/not-zip-safe
scanningegs.egg-info/requires.txt
scanningegs.egg-info/top_level.txt