Metadata-Version: 1.0
Name: scanningegs
Version: 0.0.2
Summary: Generate EGSnrc files for a scanning target
Home-page: http://github.com/henrybaxter/scanningegs
Author: Henry Baxter
Author-email: henry.baxter@gmail.com
License: MIT
Platform: UNKNOWN
